djpro/__init__.py
djpro/base.py
djpro/commands/__init__.py
djpro/commands/help.py
djpro/commands/man.py
djpro/commands/module.py
djpro/commands/project.py
djpro/utils/__init__.py
djpro/utils/django_utils.py
djpro/utils/files_content.py
djpro/utils/logging.py
djpro/utils/write_and_config.py
djpro/utils/messages/__init__.py
djpro/utils/messages/run_dev.py
djpro/utils/messages/run_prod.py
djpro-0.0.6.dist-info/AUTHORS.rst
djpro-0.0.6.dist-info/LICENSE.txt
djpro-0.0.6.dist-info/METADATA
djpro-0.0.6.dist-info/WHEEL
djpro-0.0.6.dist-info/entry_points.txt
djpro-0.0.6.dist-info/top_level.txt
djpro-0.0.6.dist-info/RECORD
