Metadata-Version: 2.1
Name: djpro
Version: 0.0.6
Summary: Package that allows you to create a Django project using a modular and scalable architecture with options like API configuration, DjangoAdminSite custom theme and Docker to optimize your development time
Home-page: https://djpro.readthedocs.io/en/latest/index.html
Author: Franco Gidaszewski
Author-email: gidaszewskifranco@gmail.com
License: MIT
Project-URL: Documentation, https://djpro.readthedocs.io/en/latest/index.html
Project-URL: Bug Tracker, https://github.com/szew404/dj-pro/issues
Project-URL: Source Code, https://github.com/szew404/dj-pro
Platform: any
Classifier: Development Status :: 4 - Beta 
Classifier: Framework :: Django
Classifier: Framework :: Django :: 2.0
Classifier: Framework :: Django :: 2.1
Classifier: Framework :: Django :: 2.2
Classifier: Framework :: Django :: 3.0
Classifier: Framework :: Django :: 3.1
Classifier: Framework :: Django :: 3.2
Classifier: Framework :: Django :: 4.0
Classifier: Framework :: Django :: 4.1
Classifier: Framework :: Django :: 4.2
Classifier: Framework :: Django :: 5
Classifier: Framework :: Django :: 5.0
Classifier: Framework :: Django :: 5.1
Classifier: Operating System :: OS Independent
Classifier: Intended Audience :: Developers
Classifier: Natural Language :: English
Classifier: Programming Language :: Python
Classifier: Programming Language :: Python :: 3
Classifier: Programming Language :: Python :: 3.6
Classifier: Programming Language :: Python :: 3.7
Classifier: Programming Language :: Python :: 3.8
Classifier: Programming Language :: Python :: 3.9
Classifier: Programming Language :: Python :: 3.10
Classifier: Programming Language :: Python :: 3.11
Classifier: Programming Language :: Python :: Implementation :: CPython
Classifier: Programming Language :: Python :: Implementation :: PyPy
Classifier: Topic :: Software Development :: Libraries :: Python Modules
Classifier: Topic :: Utilities
Classifier: License :: OSI Approved :: MIT License
Requires-Python: >=3.7
License-File: LICENSE.txt
License-File: AUTHORS.rst
Requires-Dist: django>=5.0
Requires-Dist: colorama>=0.4.6
